bearparse/__init__.py
bearparse/parsers.py
bearparse-0.3.3.dist-info/METADATA
bearparse-0.3.3.dist-info/WHEEL
bearparse-0.3.3.dist-info/RECORD
