Metadata-Version: 2.1
Name: bearparse
Version: 0.3.3
Summary: A custom argument parser for non-standard arguments. Useful for Appworx
Home-page: https://git.zevaryx.com/zevaryx/bearparse
License: GPL-3.0-or-later
Author: Zevaryx
Author-email: zevaryx@gmail.com
Requires-Python: >=3.9,<4
Classifier: License :: OSI Approved :: GNU General Public License v3 or later (GPLv3+)
Classifier: Programming Language :: Python :: 3
Classifier: Programming Language :: Python :: 3.9
Classifier: Programming Language :: Python :: 3.10
Classifier: Programming Language :: Python :: 3.11
Classifier: Programming Language :: Python :: 3.12
Requires-Dist: PyYAML (>=6.0.1,<7)
Requires-Dist: attrs (>=23.2.0)
Requires-Dist: toml (>=0.10.2,<0.11.0)
Project-URL: Repository, https://git.zevaryx.com/zevaryx/bearparse
